pypendentdrop/__init__.py
pypendentdrop/__main__.py
pypendentdrop/cli.py
pypendentdrop/logfacility.py
pypendentdrop/ppd_parse.py
pypendentdrop/ppdplot.py
pypendentdrop/analysis/__init__.py
pypendentdrop/analysis/fetchimage.py
pypendentdrop/analysis/findparameters.py
pypendentdrop/analysis/getcontour.py
pypendentdrop/gui/__init__.py
pypendentdrop/gui/__main__.py
pypendentdrop/gui/gui.py
pypendentdrop/gui/mainwindow.py
pypendentdrop/gui/mainwindow_ui.py
pypendentdrop/gui/plotwidget.py
pypendentdrop-0.1.4.dist-info/METADATA
pypendentdrop-0.1.4.dist-info/WHEEL
pypendentdrop-0.1.4.dist-info/entry_points.txt
pypendentdrop-0.1.4.dist-info/licenses/LICENSE
pypendentdrop-0.1.4.dist-info/RECORD
