Metadata-Version: 2.4
Name: pypendentdrop
Version: 0.1.4
Summary: Open-source Python API with a graphical and command-line interface to measure surface tension coefficients from images of pendent drops.
Project-URL: Homepage, https://github.com/Moryavendil/pypendentdrop
Project-URL: Issues, https://github.com/Moryavendil/pypendentdrop/issues
Author-email: G2L <GDoubleL@proton.me>
License-File: LICENSE
Keywords: analysis,drop,image,measure,pendant,pendent,surface,tension
Classifier: License :: OSI Approved :: GNU General Public License v3 (GPLv3)
Classifier: Operating System :: OS Independent
Classifier: Programming Language :: Python :: 3
Requires-Python: >=3.8
Requires-Dist: contourpy>=1.0
Requires-Dist: pillow
Requires-Dist: scipy>=1.7
Provides-Extra: cli
Requires-Dist: matplotlib; extra == 'cli'
Provides-Extra: full
Requires-Dist: matplotlib; extra == 'full'
Requires-Dist: pyqt5; extra == 'full'
Requires-Dist: pyqtgraph; extra == 'full'
Provides-Extra: gui
Requires-Dist: pyqt5; extra == 'gui'
Requires-Dist: pyqtgraph; extra == 'gui'
